{
  "units.centimeters": {
    "value": "cm",
    "history": [
      {
        "userId": 154927,
        "timestamp": 1549003193637,
        "oldValue": "",
        "newValue": "cm",
        "explanation": null
      }
    ]
  },
  "forceOnObjectByOtherObjectPattern": {
    "value": "{{otherObject}}에 의해 {{thisObject}}에 가해지는 힘",
    "history": [
      {
        "userId": 154927,
        "timestamp": 1549003193637,
        "oldValue": "",
        "newValue": "{{otherObject}}에 의해 {{thisObject}}에 가해지는 힘",
        "explanation": null
      }
    ]
  },
  "forceOnObjectByOtherObjectWithUnitsPattern": {
    "value": "{{otherObject}}에 의해 {{thisObject}}에 가해지는 힘 ={{value}}N",
    "history": [
      {
        "userId": 154927,
        "timestamp": 1549003193637,
        "oldValue": "",
        "newValue": "{{otherObject}}에 의해 {{thisObject}}에 가해지는 힘 ={{value}}N",
        "explanation": null
      }
    ]
  },
  "forceValues": {
    "value": "힘 값",
    "history": [
      {
        "userId": 154927,
        "timestamp": 1549003193637,
        "oldValue": "",
        "newValue": "힘 값",
        "explanation": null
      }
    ]
  },
  "units.picometers": {
    "value": "pm",
    "history": [
      {
        "userId": 154927,
        "timestamp": 1549003193637,
        "oldValue": "",
        "newValue": "pm",
        "explanation": null
      }
    ]
  },
  "pattern_0value_1units": {
    "value": "{{value}} {{units}}",
    "history": [
      {
        "userId": 154927,
        "timestamp": 1549003193637,
        "oldValue": "",
        "newValue": "{{value}} {{units}}",
        "explanation": null
      }
    ]
  }
}