{
  "appliedForce": {
    "value": "j",
    "history": [
      {
        "userId": 195724,
        "timestamp": 1445452257884,
        "oldValue": "",
        "newValue": "10",
        "explanation": null
      },
      {
        "userId": 195724,
        "timestamp": 1445452772002,
        "oldValue": "10",
        "newValue": "j",
        "explanation": null
      }
    ]
  },
  "appliedForceColon": {
    "value": "p",
    "history": [
      {
        "userId": 195724,
        "timestamp": 1445452257884,
        "oldValue": "",
        "newValue": "16",
        "explanation": null
      },
      {
        "userId": 195724,
        "timestamp": 1445452772002,
        "oldValue": "16",
        "newValue": "p",
        "explanation": null
      }
    ]
  },
  "appliedForceNumber": {
    "value": "17 {0}:",
    "history": [
      {
        "userId": 195724,
        "timestamp": 1445452257884,
        "oldValue": "",
        "newValue": "17 {0}:",
        "explanation": null
      }
    ]
  },
  "barGraph": {
    "value": "k",
    "history": [
      {
        "userId": 195724,
        "timestamp": 1445452257884,
        "oldValue": "",
        "newValue": "11",
        "explanation": null
      },
      {
        "userId": 195724,
        "timestamp": 1445452772002,
        "oldValue": "11",
        "newValue": "k",
        "explanation": null
      }
    ]
  },
  "bottomSpring": {
    "value": "21",
    "history": [
      {
        "userId": 195724,
        "timestamp": 1445452257884,
        "oldValue": "",
        "newValue": "21",
        "explanation": null
      }
    ]
  },
  "components": {
    "value": "25",
    "history": [
      {
        "userId": 195724,
        "timestamp": 1445452257884,
        "oldValue": "",
        "newValue": "25",
        "explanation": null
      }
    ]
  },
  "displacement": {
    "value": "c",
    "history": [
      {
        "userId": 195724,
        "timestamp": 1445452257884,
        "oldValue": "",
        "newValue": "3",
        "explanation": null
      },
      {
        "userId": 195724,
        "timestamp": 1445452772002,
        "oldValue": "3",
        "newValue": "c",
        "explanation": null
      }
    ]
  },
  "displacementColon": {
    "value": "f",
    "history": [
      {
        "userId": 195724,
        "timestamp": 1445452257884,
        "oldValue": "",
        "newValue": "6",
        "explanation": null
      },
      {
        "userId": 195724,
        "timestamp": 1445452772002,
        "oldValue": "6",
        "newValue": "f",
        "explanation": null
      }
    ]
  },
  "energy": {
    "value": "m",
    "history": [
      {
        "userId": 195724,
        "timestamp": 1445452257884,
        "oldValue": "",
        "newValue": "13",
        "explanation": null
      },
      {
        "userId": 195724,
        "timestamp": 1445452772002,
        "oldValue": "13",
        "newValue": "m",
        "explanation": null
      }
    ]
  },
  "energyPlot": {
    "value": "l",
    "history": [
      {
        "userId": 195724,
        "timestamp": 1445452257884,
        "oldValue": "",
        "newValue": "12",
        "explanation": null
      },
      {
        "userId": 195724,
        "timestamp": 1445452772002,
        "oldValue": "12",
        "newValue": "l",
        "explanation": null
      }
    ]
  },
  "equilibriumPosition": {
    "value": "i",
    "history": [
      {
        "userId": 195724,
        "timestamp": 1445452257884,
        "oldValue": "",
        "newValue": "9",
        "explanation": null
      },
      {
        "userId": 195724,
        "timestamp": 1445452772002,
        "oldValue": "9",
        "newValue": "i",
        "explanation": null
      }
    ]
  },
  "forcePlot": {
    "value": "n",
    "history": [
      {
        "userId": 195724,
        "timestamp": 1445452257884,
        "oldValue": "",
        "newValue": "14",
        "explanation": null
      },
      {
        "userId": 195724,
        "timestamp": 1445452772002,
        "oldValue": "14",
        "newValue": "n",
        "explanation": null
      }
    ]
  },
  "hookes-law.title": {
    "value": "28",
    "history": [
      {
        "userId": 195724,
        "timestamp": 1445452257884,
        "oldValue": "",
        "newValue": "28",
        "explanation": null
      }
    ]
  },
  "intro": {
    "value": "20",
    "history": [
      {
        "userId": 195724,
        "timestamp": 1445452257884,
        "oldValue": "",
        "newValue": "20",
        "explanation": null
      }
    ]
  },
  "joules": {
    "value": "a",
    "history": [
      {
        "userId": 195724,
        "timestamp": 1445452257884,
        "oldValue": "",
        "newValue": "1",
        "explanation": null
      },
      {
        "userId": 195724,
        "timestamp": 1445452772002,
        "oldValue": "1",
        "newValue": "a",
        "explanation": null
      }
    ]
  },
  "leftSpring": {
    "value": "23",
    "history": [
      {
        "userId": 195724,
        "timestamp": 1445452257884,
        "oldValue": "",
        "newValue": "23",
        "explanation": null
      }
    ]
  },
  "meters": {
    "value": "d",
    "history": [
      {
        "userId": 195724,
        "timestamp": 1445452257884,
        "oldValue": "",
        "newValue": "4",
        "explanation": null
      },
      {
        "userId": 195724,
        "timestamp": 1445452772002,
        "oldValue": "4",
        "newValue": "d",
        "explanation": null
      }
    ]
  },
  "newtons": {
    "value": "e",
    "history": [
      {
        "userId": 195724,
        "timestamp": 1445452257884,
        "oldValue": "",
        "newValue": "5",
        "explanation": null
      },
      {
        "userId": 195724,
        "timestamp": 1445452772002,
        "oldValue": "5",
        "newValue": "e",
        "explanation": null
      }
    ]
  },
  "newtonsPerMeter": {
    "value": "g",
    "history": [
      {
        "userId": 195724,
        "timestamp": 1445452257884,
        "oldValue": "",
        "newValue": "7",
        "explanation": null
      },
      {
        "userId": 195724,
        "timestamp": 1445452772002,
        "oldValue": "7",
        "newValue": "g",
        "explanation": null
      }
    ]
  },
  "pattern.0value.1units": {
    "value": "{1} {0}",
    "history": [
      {
        "userId": 195724,
        "timestamp": 1445452257884,
        "oldValue": "",
        "newValue": "{1} {0}",
        "explanation": null
      }
    ]
  },
  "potentialEnergy": {
    "value": "b",
    "history": [
      {
        "userId": 195724,
        "timestamp": 1445452257884,
        "oldValue": "",
        "newValue": "2",
        "explanation": null
      },
      {
        "userId": 195724,
        "timestamp": 1445452772002,
        "oldValue": "2",
        "newValue": "b",
        "explanation": null
      }
    ]
  },
  "rightSpring": {
    "value": "24",
    "history": [
      {
        "userId": 195724,
        "timestamp": 1445452257884,
        "oldValue": "",
        "newValue": "24",
        "explanation": null
      }
    ]
  },
  "springConstant": {
    "value": "h",
    "history": [
      {
        "userId": 195724,
        "timestamp": 1445452257884,
        "oldValue": "",
        "newValue": "8",
        "explanation": null
      },
      {
        "userId": 195724,
        "timestamp": 1445452772002,
        "oldValue": "8",
        "newValue": "h",
        "explanation": null
      }
    ]
  },
  "springConstantNumber": {
    "value": "18 {0}:",
    "history": [
      {
        "userId": 195724,
        "timestamp": 1445452257884,
        "oldValue": "",
        "newValue": "18 {0}:",
        "explanation": null
      }
    ]
  },
  "springForce": {
    "value": "19",
    "history": [
      {
        "userId": 195724,
        "timestamp": 1445452257884,
        "oldValue": "",
        "newValue": "19",
        "explanation": null
      }
    ]
  },
  "systems": {
    "value": "27",
    "history": [
      {
        "userId": 195724,
        "timestamp": 1445452257884,
        "oldValue": "",
        "newValue": "27",
        "explanation": null
      }
    ]
  },
  "topSpring": {
    "value": "22",
    "history": [
      {
        "userId": 195724,
        "timestamp": 1445452257884,
        "oldValue": "",
        "newValue": "22",
        "explanation": null
      }
    ]
  },
  "total": {
    "value": "26",
    "history": [
      {
        "userId": 195724,
        "timestamp": 1445452257884,
        "oldValue": "",
        "newValue": "26",
        "explanation": null
      }
    ]
  },
  "values": {
    "value": "o",
    "history": [
      {
        "userId": 195724,
        "timestamp": 1445452257884,
        "oldValue": "",
        "newValue": "15",
        "explanation": null
      },
      {
        "userId": 195724,
        "timestamp": 1445452772002,
        "oldValue": "15",
        "newValue": "o",
        "explanation": null
      }
    ]
  }
}