{
  "energy.kinetic": {
    "value": "Kinetik"
  },
  "energy.total": {
    "value": "Total"
  },
  "units.meters-per-second": {
    "value": "meter/detik"
  },
  "forces.work-energy-title": {
    "value": "Usaha/Energi"
  },
  "object.custom-crate": {
    "value": "Ubah Peti Kayu"
  },
  "module.coordinates": {
    "value": "Koordinat"
  },
  "forces.parallel-applied": {
    "value": "Gaya Terapan Paralel"
  },
  "energy.kinetic-energy": {
    "value": "Energi Kinetik"
  },
  "ramp.height-indicator": {
    "value": "h = {0} m"
  },
  "the-ramp-1.description": {
    "value": "Gaya pada Bidang Miring"
  },
  "energy.thermal": {
    "value": "Panas "
  },
  "confirm-clear-graphs": {
    "value": "Apa Anda yakin hendak menghapus grafik ini?"
  },
  "time.playback": {
    "value": "Mainkan"
  },
  "force.abbrev.applied": {
    "value": "a"
  },
  "coordinates.frames": {
    "value": "Bingkai Koordinat"
  },
  "controls.sound": {
    "value": "Suara"
  },
  "forces-and-friction.module.graphing.title": {
    "value": "Grafik"
  },
  "translation.credits": {
    "value": "Anne Sirait\nSTKIP - Surya\nannesirait@gmail.com / annesirait@stkipsurya.ac.id"
  },
  "force.abbrev.wall": {
    "value": "w"
  },
  "object.small-crate": {
    "value": "Peti Kecil"
  },
  "robot-moving-company.name": {
    "value": "Perusahaan Robot Bergerak"
  },
  "controls.clear": {
    "value": "Hapus"
  },
  "vectors.centered": {
    "value": "Tengah"
  },
  "message.overheated": {
    "value": "Terlalu Panas"
  },
  "surface.concrete": {
    "value": "Beton"
  },
  "property.position": {
    "value": "Posisi"
  },
  "object.dog": {
    "value": "Anjing "
  },
  "vectors.force-vectors": {
    "value": "Vektor - Vektor Gaya"
  },
  "forces.parallel-friction": {
    "value": "Gesekan Paralel"
  },
  "coordinates.x-components": {
    "value": "Komponen X"
  },
  "confirm-reset": {
    "value": "Apakah Anda yakin hendak mengatur ulang semuanya?"
  },
  "forces-and-friction.module.friction.title": {
    "value": "Gesekan"
  },
  "vectors.parallel-components": {
    "value": "Komponen Paralel"
  },
  "0.work": {
    "value": "{0} Usaha"
  },
  "coordinates.coordinate-system": {
    "value": "Sistem Koordinat"
  },
  "camera.zoom-out": {
    "value": "Perkecil"
  },
  "forces.applied-force": {
    "value": "Gaya Terapan"
  },
  "module.introduction": {
    "value": "Pendahuluan"
  },
  "object.description.pattern.name_mass": {
    "value": "{0} ({1} kg)"
  },
  "time.rewind": {
    "value": "Ulang"
  },
  "display.bar-graph": {
    "value": "Grafik Batang"
  },
  "forces.normal": {
    "value": "Normal"
  },
  "module.force-graphs": {
    "value": "Grafik Gaya"
  },
  "controls.showWorkEnergyCharts": {
    "value": "Tunjukkan Grafik Usaha/Energi"
  },
  "units.abbr.newtons": {
    "value": "N"
  },
  "vectors.point-of-origin": {
    "value": "Titik Awal"
  },
  "work.friction-work": {
    "value": "Usaha Gesekan"
  },
  "object.textbook": {
    "value": "Buku Bacaan"
  },
  "controls.hide-free-body-diagram": {
    "value": "Diagram Gaya - Gaya"
  },
  "controls.no-friction": {
    "value": "Tidak ada gesekan"
  },
  "the-ramp.description": {
    "value": "Gaya pada Bidang Miring"
  },
  "coordinates.entire-vectors": {
    "value": "Seluruh Vektor"
  },
  "vectors.x-y-components": {
    "value": "Komponen X-Y"
  },
  "units.abbr.meters": {
    "value": "m"
  },
  "ramp.controls.title": {
    "value": "Pengatur Lereng"
  },
  "coordinates.y": {
    "value": "y"
  },
  "coordinates.x": {
    "value": "x"
  },
  "force.abbrev.normal": {
    "value": "N"
  },
  "symbols.perpendicular": {
    "value": "⊥"
  },
  "object.refrigerator": {
    "value": "Lemari Es"
  },
  "property.coefficient-of-static-friction": {
    "value": "Koefisien Gesek Statis"
  },
  "work.friction": {
    "value": "Gesekan"
  },
  "coordinates.adjustable": {
    "value": "Sesuaikan"
  },
  "object.file-cabinet": {
    "value": "Lemari Berkas"
  },
  "module.work-energy": {
    "value": "Usaha/Energi"
  },
  "forces-and-friction.module.intro.title": {
    "value": "Pendahuluan"
  },
  "surface.ice": {
    "value": "Es"
  },
  "camera.zoom-in": {
    "value": "Perbesar"
  },
  "property.mass": {
    "value": "Massa"
  },
  "time.pause": {
    "value": "Jeda"
  },
  "vectors.sum-of-forces": {
    "value": "Jumlah Gaya"
  },
  "units.abbr.joules": {
    "value": "J"
  },
  "work.applied": {
    "value": "Terapkan"
  },
  "property.coefficient-of-kinetic-friction": {
    "value": "Koefisien Gesek Kinetik"
  },
  "module.robotMovingCompany": {
    "value": "Perusahaan Robot Bergerak"
  },
  "energy.total-energy": {
    "value": "Energi Total"
  },
  "controls.friction": {
    "value": "Gesekan"
  },
  "forces.total": {
    "value": "Total"
  },
  "energy.thermal-energy": {
    "value": "Energi Panas"
  },
  "object.mystery-object": {
    "value": "Benda Misterius"
  },
  "indicator.height": {
    "value": "h=0.0 @ y={0}"
  },
  "forces.parallel-title-with-units": {
    "value": "Gaya Paralel (N)"
  },
  "force.abbrev.total": {
    "value": "jumlah"
  },
  "forces.applied": {
    "value": "Terapkan"
  },
  "display.free-body-diagram": {
    "value": "Diagram Gaya - Gaya"
  },
  "forces.parallel-gravity": {
    "value": "Gaya Gravitasi Paralel"
  },
  "controls.work-energy-charts": {
    "value": "Grafik Usaha/Energi"
  },
  "confirm.reset.title": {
    "value": "Konfirmasi Atur Ulang"
  },
  "units.meters": {
    "value": "meter"
  },
  "time.go": {
    "value": "Jalan!"
  },
  "energy.work": {
    "value": "Usaha"
  },
  "controls.lots-of-friction": {
    "value": "Banyak Gesekan"
  },
  "readout.mass": {
    "value": "{0} ({1} kg)"
  },
  "readout.velocity": {
    "value": "{0} m/s"
  },
  "time.record": {
    "value": "Rekam"
  },
  "readout.graph-name": {
    "value": "{0} Grafik"
  },
  "time.slow-motion": {
    "value": "Gerak Lambat"
  },
  "controls.forces.maximize": {
    "value": "Gaya >>>"
  },
  "coordinates.y-components": {
    "value": "Komponen Y"
  },
  "0.energy": {
    "value": "{0} Energi"
  },
  "robot-moving-company.description": {
    "value": "Perusahaan Robot Bergerak"
  },
  "controls.applied-force-x": {
    "value": "Terapkan Gaya X"
  },
  "units.newtons": {
    "value": "Newton"
  },
  "work.applied-work": {
    "value": "Usaha Terapan "
  },
  "object.position": {
    "value": "Posisi Benda"
  },
  "display.graphs": {
    "value": "Grafik"
  },
  "force.abbrev.gravity": {
    "value": "g"
  },
  "forces.Wall": {
    "value": "Dinding"
  },
  "controls.frictionless": {
    "value": "Licin"
  },
  "coordinates.perpendicular-components": {
    "value": "Komponen Tegak Lurus"
  },
  "units.joules": {
    "value": "Joule"
  },
  "confirm.clear": {
    "value": "Konfirmasi Hapus"
  },
  "controls.measuring-tape": {
    "value": "Pita Ukur"
  },
  "controls.show": {
    "value": "Tunjukkan"
  },
  "energy.energy": {
    "value": "Energi"
  },
  "forces.parallel-title": {
    "value": "Gaya Paralel"
  },
  "indicator.height-unknown": {
    "value": "h=???"
  },
  "forces.Gravity": {
    "value": "Gravitasi"
  },
  "forces.work-energy-title-with-units": {
    "value": "Usaha/Energi (J)"
  },
  "forces.applied.n": {
    "value": "Gaya Terapan (N)"
  },
  "controls.cool-ramp": {
    "value": "Pendingin Bidang Miring"
  },
  "forces.Net": {
    "value": "Jumlah"
  },
  "controls.hide": {
    "value": "Sembunyikan"
  },
  "units.degrees": {
    "value": "derajat"
  },
  "chart.series-readout.pattern.value_units": {
    "value": "= {0} {1}"
  },
  "object.piano": {
    "value": "Piano"
  },
  "indicator.height-zero": {
    "value": "h=0.0 m"
  },
  "forces.parallel": {
    "value": "Gaya Paralel"
  },
  "indicator.height-meters": {
    "value": "h={0} m"
  },
  "forces-and-friction.description": {
    "value": "Gaya dan Gesekan pada Bidang Miring"
  },
  "controls.show-free-body-diagram": {
    "value": "Diagram Gaya - Gaya"
  },
  "forces.kinetic-friction": {
    "value": "Gesekan Kinetik"
  },
  "surface.carpet": {
    "value": "Karpet"
  },
  "controls.clear-heat": {
    "value": "Hapus Panas"
  },
  "controls.velocity": {
    "value": "Kecepatan"
  },
  "controls.controls": {
    "value": "Pengatur"
  },
  "controls.show-zero-point-pe": {
    "value": "Tunjukkan titik nol EP"
  },
  "force.abbrev.friction": {
    "value": "f"
  },
  "controls.choose-object": {
    "value": "Pilih Benda"
  },
  "ramp.angle-readout": {
    "value": "Sudut = {0} °"
  },
  "forces.parallel-wall": {
    "value": "Gaya Dinding Paralel"
  },
  "symbols.parallel": {
    "value": "II"
  },
  "property.coefficient-of-friction": {
    "value": "Koefisien Gesek"
  },
  "energy.potential-energy": {
    "value": "Energi Potensial"
  },
  "coordinates.parallel-components": {
    "value": "Komponen Paralel"
  },
  "forces-and-friction.module.robot-moving-company.title": {
    "value": "Perusahaan Robot Bergerak"
  },
  "object.crate": {
    "value": "Peti Kayu"
  },
  "vectors.title": {
    "value": "Vektor"
  },
  "coordinates.fixed": {
    "value": "Tetap"
  },
  "forces.friction": {
    "value": "gesekan"
  },
  "controls.reset": {
    "value": "Atur Ulang"
  },
  "work.gravity": {
    "value": "Gravitasi"
  },
  "the-ramp.name": {
    "value": "Bidang Miring"
  },
  "forces-and-friction.name": {
    "value": "Gaya dan Gesekan"
  },
  "forces.weight": {
    "value": "Berat"
  },
  "units.abbr.kg": {
    "value": "kg"
  },
  "property.ramp-angle": {
    "value": "Sudut Lereng"
  },
  "readout.seconds": {
    "value": "{0} detik"
  },
  "module.more-features": {
    "value": "Fitur Tambahan"
  },
  "the-ramp-1.name": {
    "value": "Bidang Miring (1.00 series)"
  },
  "energy.potential": {
    "value": "Potensial"
  },
  "controls.forces-to-show": {
    "value": "Tunjukkan Gaya"
  },
  "work.gravity-work": {
    "value": "Usaha Gravitasi"
  },
  "forces.static-friction": {
    "value": "Gesekan Statis"
  }
}
