{
  "screen.compare": {
    "value": "Муқоиса",
    "history": [
      {
        "userId": 900124,
        "timestamp": 1643392233854,
        "oldValue": "",
        "newValue": "Муқоиса"
      }
    ]
  },
  "screen.intro": {
    "value": "Муқаддима",
    "history": [
      {
        "userId": 900124,
        "timestamp": 1643392233854,
        "oldValue": "",
        "newValue": "Муқаддима"
      }
    ]
  },
  "screen.mystery": {
    "value": "Номаълум",
    "history": [
      {
        "userId": 900124,
        "timestamp": 1643392233854,
        "oldValue": "",
        "newValue": "Номаълум"
      }
    ]
  },
  "density.title": {
    "value": "Зиччӣ",
    "history": [
      {
        "userId": 900124,
        "timestamp": 1643392233854,
        "oldValue": "",
        "newValue": "Зиччӣ"
      }
    ]
  }
}