{
  "arrowKeysMoveFoot": {
    "value": "<strong>Butonat e majtë ose të djathtë të shigjetave</strong> lëvize dorën ose këmbën.",
    "history": [
      {
        "userId": 760140,
        "timestamp": 1586260560208,
        "oldValue": "",
        "newValue": "<strong>Butonat e majtë ose të djathtë të shigjetave</strong> lëvize dorën ose këmbën.",
        "explanation": null
      }
    ]
  },
  "escapeKeyDescription": {
    "value": "<strong>Butoni Escape</strong> e mbyll një dialog,si ky.",
    "history": [
      {
        "userId": 760140,
        "timestamp": 1586260560208,
        "oldValue": "",
        "newValue": "<strong>Butoni Escape</strong> e mbyll një dialog,si ky.",
        "explanation": null
      }
    ]
  },
  "escKey": {
    "value": "Esc",
    "history": [
      {
        "userId": 760140,
        "timestamp": 1586260560208,
        "oldValue": "",
        "newValue": "Esc",
        "explanation": null
      }
    ]
  },
  "hotKeysAndHelp": {
    "value": "Shkurtesat e tastaturës",
    "history": [
      {
        "userId": 760140,
        "timestamp": 1586260560208,
        "oldValue": "",
        "newValue": "Shkurtesat e tastaturës",
        "explanation": null
      }
    ]
  },
  "or": {
    "value": "ose",
    "history": [
      {
        "userId": 760140,
        "timestamp": 1586260560208,
        "oldValue": "",
        "newValue": "ose",
        "explanation": null
      }
    ]
  },
  "shiftKey": {
    "value": "Shift",
    "history": [
      {
        "userId": 760140,
        "timestamp": 1586260560208,
        "oldValue": "",
        "newValue": "Shift",
        "explanation": null
      }
    ]
  },
  "shiftTabKeyDescription": {
    "value": "<strong>Shift plus Tab</strong> kalon në objektin paraprak.",
    "history": [
      {
        "userId": 760140,
        "timestamp": 1586260560208,
        "oldValue": "",
        "newValue": "<strong>Shift plus Tab</strong> kalon në objektin paraprak.",
        "explanation": null
      }
    ]
  },
  "tabKeyDescription": {
    "value": "<strong>butoni Tab</strong> kalon në objektin e ardhshëm.",
    "history": [
      {
        "userId": 760140,
        "timestamp": 1586260560208,
        "oldValue": "",
        "newValue": "<strong>butoni Tab</strong> kalon në objektin e ardhshëm.",
        "explanation": null
      }
    ]
  },
  "tabKey": {
    "value": "Tab",
    "history": [
      {
        "userId": 760140,
        "timestamp": 1586260560208,
        "oldValue": "",
        "newValue": "Tab",
        "explanation": null
      }
    ]
  },
  "handOrFoot": {
    "value": "Dora ose Këmba",
    "history": [
      {
        "userId": 760140,
        "timestamp": 1586260560208,
        "oldValue": "",
        "newValue": "Dora ose Këmba",
        "explanation": null
      }
    ]
  },
  "moveHandOrFoot": {
    "value": "Lëvize dorën ose këmbën",
    "history": [
      {
        "userId": 760140,
        "timestamp": 1586260560208,
        "oldValue": "",
        "newValue": "Lëvize dorën ose këmbën",
        "explanation": null
      }
    ]
  },
  "john-travoltage.title": {
    "value": "John Travoltage",
    "history": [
      {
        "userId": 760140,
        "timestamp": 1586260560208,
        "oldValue": "",
        "newValue": "John Travoltage",
        "explanation": null
      }
    ]
  }
}