{
  "none": {
    "value": "Không"
  },
  "force": {
    "value": "Lực"
  },
  "values": {
    "value": "Trị số"
  },
  "redWins": {
    "value": "Đỏ thắng!"
  },
  "frictionForce": {
    "value": "Lực ma sát"
  },
  "pause": {
    "value": "Dừng"
  },
  "friction": {
    "value": "Ma sát"
  },
  "forces-and-motion-basics.title": {
    "value": "Lực và chuyển động: Những điều cơ bản"
  },
  "appliedForce": {
    "value": "Lực tác dụng"
  },
  "leftForce": {
    "value": "Lực bên trái"
  },
  "pattern.0massUnitsKilograms": {
    "value": "{0}kg"
  },
  "rightForce": {
    "value": "Lực bên phải"
  },
  "acceleration": {
    "value": "Gia tốc"
  },
  "lots": {
    "value": "Nhiều"
  },
  "forces": {
    "value": "Lực"
  },
  "motion": {
    "value": "Chuyển động"
  },
  "netForce": {
    "value": "Kéo co"
  },
  "go": {
    "value": "Kéo!"
  },
  "sumOfForcesEqualsZero": {
    "value": "Tổng lực = 0"
  },
  "blueWins": {
    "value": "Xanh thắng!"
  },
  "speed": {
    "value": "Tốc độ"
  },
  "sumOfForces": {
    "value": "Tổng lực"
  },
  "return": {
    "value": "Trả lại như cũ"
  },
  "masses": {
    "value": "Khối lượng"
  },
  "pattern.0valueUnitsN": {
    "value": "{0}N"
  }
}